python_code_parse/__init__.py
python_code_parse/function_returns.py
python_code_parse/get_all_function_info_from_code.py
python_code_parse/get_function_indentation_str.py
python_code_parse/get_function_info_by_name.py
python_code_parse/replace_function_signature.py
python_code_parse/enums/special_arg.py
python_code_parse/exceptions/__init__.py
python_code_parse/exceptions/function_not_found_exception.py
python_code_parse/models/__init__.py
python_code_parse/models/function_arg.py
python_code_parse/models/function_info.py
python_code_parse/utils/get_function_arg_from_ast_arg.py
python_code_parse-0.0.14.dist-info/METADATA
python_code_parse-0.0.14.dist-info/WHEEL
python_code_parse-0.0.14.dist-info/top_level.txt
python_code_parse-0.0.14.dist-info/RECORD
