Metadata-Version: 2.1
Name: python-code-parse
Version: 0.0.14
Summary: Parse code to get information about functions, etc.
Author-email: Jake Cyr <cyrjake@gmail.com>
License: MIT
Keywords: code,parse,python,ast,abstract syntax tree
Classifier: Intended Audience :: Developers
Classifier: License :: OSI Approved :: MIT License
Classifier: Programming Language :: Python :: 3
Requires-Python: >=3.7
Provides-Extra: dev
Requires-Dist: twine ; extra == 'dev'
Requires-Dist: wheel ; extra == 'dev'
Requires-Dist: black ; extra == 'dev'
Requires-Dist: isort ; extra == 'dev'
Requires-Dist: flake8 ; extra == 'dev'
